tentaclio_gdrive/__init__.py
tentaclio_gdrive/__main__.py
tentaclio_gdrive/clients/__init__.py
tentaclio_gdrive/clients/google_drive_client.py
tentaclio_gdrive-0.0.3.dist-info/LICENSE.txt
tentaclio_gdrive-0.0.3.dist-info/METADATA
tentaclio_gdrive-0.0.3.dist-info/WHEEL
tentaclio_gdrive-0.0.3.dist-info/top_level.txt
tentaclio_gdrive-0.0.3.dist-info/RECORD
