Metadata-Version: 2.1
Name: tentaclio-gdrive
Version: 0.0.3
Summary: A python project containing all the dependencies for schema gdrive for tentaclio.
Home-page: UNKNOWN
Author: Octopus Energy
Author-email: nerds@octopus.energy
License: Proprietary
Platform: UNKNOWN
Classifier: Intended Audience :: Developers
Classifier: Operating System :: OS Independent
Classifier: Programming Language :: Python
Classifier: Programming Language :: Python :: 3
Classifier: Programming Language :: Python :: 3.6
Classifier: Programming Language :: Python :: 3.7
Classifier: Programming Language :: Python :: 3.8
Classifier: Programming Language :: Python :: 3.9
License-File: LICENSE.txt
Requires-Dist: tentaclio (>=1.0.2)
Requires-Dist: google-api-python-client
Requires-Dist: google-auth-httplib2
Requires-Dist: google-auth-oauthlib
